LICENCE.txt
MANIFEST.in
README.rst
setup.py
emencia_paste_djangocms_3/__init__.py
emencia_paste_djangocms_3/templates.py
emencia_paste_djangocms_3.egg-info/PKG-INFO
emencia_paste_djangocms_3.egg-info/SOURCES.txt
emencia_paste_djangocms_3.egg-info/dependency_links.txt
emencia_paste_djangocms_3.egg-info/entry_points.txt
emencia_paste_djangocms_3.egg-info/not-zip-safe
emencia_paste_djangocms_3.egg-info/requires.txt
emencia_paste_djangocms_3.egg-info/top_level.txt
emencia_paste_djangocms_3/django_buildout/+dot+gitignore
emencia_paste_djangocms_3/django_buildout/Makefile_tmpl
emencia_paste_djangocms_3/django_buildout/README.rst
emencia_paste_djangocms_3/django_buildout/bootstrap.py
emencia_paste_djangocms_3/django_buildout/buildout.cfg_tmpl
emencia_paste_djangocms_3/django_buildout/development.cfg
emencia_paste_djangocms_3/django_buildout/integration.cfg
emencia_paste_djangocms_3/django_buildout/production.cfg
emencia_paste_djangocms_3/django_buildout/versions.cfg
emencia_paste_djangocms_3/django_buildout/compass/+dot+gitignore
emencia_paste_djangocms_3/django_buildout/compass/README.rst
emencia_paste_djangocms_3/django_buildout/compass/config.rb
emencia_paste_djangocms_3/django_buildout/compass/config_admin-style.rb
emencia_paste_djangocms_3/django_buildout/compass/admin_style/_settings.scss
emencia_paste_djangocms_3/django_buildout/compass/admin_style/djangocms-admin-frontend.scss
emencia_paste_djangocms_3/django_buildout/compass/admin_style/djangocms-admin.scss
emencia_paste_djangocms_3/django_buildout/compass/admin_style/ie.scss
emencia_paste_djangocms_3/django_buildout/compass/admin_style/libs/_html5-boilerplate.scss
emencia_paste_djangocms_3/django_buildout/compass/admin_style/libs/_normalize.scss
emencia_paste_djangocms_3/django_buildout/compass/admin_style/libs/html5-boilerplate/_fonts.scss
emencia_paste_djangocms_3/django_buildout/compass/admin_style/libs/html5-boilerplate/_helpers.scss
emencia_paste_djangocms_3/django_buildout/compass/admin_style/libs/html5-boilerplate/_media.scss
emencia_paste_djangocms_3/django_buildout/compass/admin_style/libs/html5-boilerplate/_reset.scss
emencia_paste_djangocms_3/django_buildout/compass/admin_style/libs/html5-boilerplate/_styles.scss
emencia_paste_djangocms_3/django_buildout/compass/admin_style/partials/_base.scss
