Metadata-Version: 1.1
Name: emencia-paste-djangocms-3
Version: 1.4.0
Summary: Epaster template to build DjangoCMS 3.x projects
Home-page: https://github.com/emencia/emencia_paste_djangocms_3
Author: David Thenon
Author-email: dthenon@emencia.com
License: MIT
Platform: UNKNOWN
Classifier: Programming Language :: Python
Classifier: Programming Language :: Python :: 2.7
Classifier: License :: OSI Approved :: MIT License
Classifier: Operating System :: OS Independent
Classifier: Development Status :: 5 - Production/Stable
Classifier: Environment :: Web Environment
Classifier: Framework :: Paste
Classifier: Intended Audience :: Developers
Classifier: Topic :: Software Development :: Libraries :: Python Modules
